aind_smartspim_operator_utils/__init__.py
aind_smartspim_operator_utils/runplan/__init__.py
aind_smartspim_operator_utils/runplan/acq_runplan.py
aind_smartspim_operator_utils-0.0.3.dist-info/LICENSE
aind_smartspim_operator_utils-0.0.3.dist-info/METADATA
aind_smartspim_operator_utils-0.0.3.dist-info/WHEEL
aind_smartspim_operator_utils-0.0.3.dist-info/top_level.txt
aind_smartspim_operator_utils-0.0.3.dist-info/RECORD
